confiy/__init__.py
confiy/confiy.py
confiy-1.4.dist-info/LICENSE.md
confiy-1.4.dist-info/METADATA
confiy-1.4.dist-info/WHEEL
confiy-1.4.dist-info/top_level.txt
confiy-1.4.dist-info/RECORD
