Metadata-Version: 2.1
Name: confiy
Version: 1.4
Summary: With this module you can easy take the value of config file only by key, in python projects
Home-page: https://github.com/hasansajedi/confiy
Author: Hasan Sajedi
Author-email: hassansajedi@gmail.com
License: UNKNOWN
Platform: UNKNOWN
Classifier: Programming Language :: Python :: 2
Classifier: License :: OSI Approved :: MIT License
Classifier: Operating System :: OS Independent
